pyrus_orm/__init__.py
pyrus_orm/catalog.py
pyrus_orm/fields.py
pyrus_orm/manager.py
pyrus_orm/model.py
pyrus_orm/py.typed
pyrus_orm/session.py
pyrus_orm/task.json
pyrus_orm/types.py
pyrus_orm/utils.py
pyrus_orm-0.0.11.dist-info/LICENSE
pyrus_orm-0.0.11.dist-info/WHEEL
pyrus_orm-0.0.11.dist-info/METADATA
pyrus_orm-0.0.11.dist-info/RECORD
